azure/mgmt/quota/__init__.py
azure/mgmt/quota/_client.py
azure/mgmt/quota/_configuration.py
azure/mgmt/quota/_patch.py
azure/mgmt/quota/_version.py
azure/mgmt/quota/py.typed
azure/mgmt/quota/_utils/__init__.py
azure/mgmt/quota/_utils/model_base.py
azure/mgmt/quota/_utils/serialization.py
azure/mgmt/quota/aio/__init__.py
azure/mgmt/quota/aio/_client.py
azure/mgmt/quota/aio/_configuration.py
azure/mgmt/quota/aio/_patch.py
azure/mgmt/quota/aio/operations/__init__.py
azure/mgmt/quota/aio/operations/_operations.py
azure/mgmt/quota/aio/operations/_patch.py
azure/mgmt/quota/models/__init__.py
azure/mgmt/quota/models/_enums.py
azure/mgmt/quota/models/_models.py
azure/mgmt/quota/models/_patch.py
azure/mgmt/quota/operations/__init__.py
azure/mgmt/quota/operations/_operations.py
azure/mgmt/quota/operations/_patch.py
azure_mgmt_quota-3.0.1.dist-info/licenses/LICENSE
azure_mgmt_quota-3.0.1.dist-info/METADATA
azure_mgmt_quota-3.0.1.dist-info/WHEEL
azure_mgmt_quota-3.0.1.dist-info/top_level.txt
azure_mgmt_quota-3.0.1.dist-info/RECORD
