Metadata-Version: 2.4
Name: azure-mgmt-quota
Version: 3.0.1
Summary: Microsoft Azure Quota Management Client Library for Python
Author-email: Microsoft Corporation <azpysdkhelp@microsoft.com>
License-Expression: MIT
Project-URL: repository, https://github.com/Azure/azure-sdk-for-python
Keywords: azure,azure sdk
Classifier: Development Status :: 5 - Production/Stable
Classifier: Programming Language :: Python
Classifier: Programming Language :: Python :: 3 :: Only
Classifier: Programming Language :: Python :: 3
Classifier: Programming Language :: Python :: 3.9
Classifier: Programming Language :: Python :: 3.10
Classifier: Programming Language :: Python :: 3.11
Classifier: Programming Language :: Python :: 3.12
Classifier: Programming Language :: Python :: 3.13
Requires-Python: >=3.9
License-File: LICENSE
Requires-Dist: isodate>=0.6.1
Requires-Dist: azure-mgmt-core>=1.6.0
Requires-Dist: typing-extensions>=4.6.0
Dynamic: license-file
